pysemgenjar_packr-0.1.3.dist-info/METADATA
pysemgenjar_packr-0.1.3.dist-info/RECORD
pysemgenjar_packr-0.1.3.dist-info/WHEEL
pysemgenjar_packr-0.1.3.dist-info/top_level.txt
semgenjar/SemSimAPI.jar
semgenjar/__init__.py
semgenjar/config.json
semgenjar/semgenapi
semgenjar/jre/ASSEMBLY_EXCEPTION
semgenjar/jre/LICENSE
semgenjar/jre/THIRD_PARTY_README
semgenjar/jre/bin/java
semgenjar/jre/bin/jjs
semgenjar/jre/bin/keytool
semgenjar/jre/bin/orbd
semgenjar/jre/bin/pack200
semgenjar/jre/bin/policytool
semgenjar/jre/bin/rmid
semgenjar/jre/bin/rmiregistry
semgenjar/jre/bin/servertool
semgenjar/jre/bin/tnameserv
semgenjar/jre/bin/unpack200
semgenjar/jre/lib/calendars.properties
semgenjar/jre/lib/charsets.jar
semgenjar/jre/lib/classlist
semgenjar/jre/lib/content-types.properties
semgenjar/jre/lib/currency.data
semgenjar/jre/lib/flavormap.properties
semgenjar/jre/lib/hijrah-config-umalqura.properties
semgenjar/jre/lib/jce.jar
semgenjar/jre/lib/jexec
semgenjar/jre/lib/jsse.jar
semgenjar/jre/lib/jvm.hprof.txt
semgenjar/jre/lib/logging.properties
semgenjar/jre/lib/management-agent.jar
semgenjar/jre/lib/meta-index
semgenjar/jre/lib/net.properties
semgenjar/jre/lib/psfont.properties.ja
semgenjar/jre/lib/psfontj2d.properties
semgenjar/jre/lib/resources.jar
semgenjar/jre/lib/rt.jar
semgenjar/jre/lib/sound.properties
semgenjar/jre/lib/tzdb.dat
