Metadata-Version: 2.1
Name: pysemgenjar-packr
Version: 0.1.3
Summary: Jar file and embedded openjdk for pysemgen
Home-page: UNKNOWN
Author: J. Kyle Medley
Author-email: UNKNOWN
License: UNKNOWN
Platform: UNKNOWN
